<annotation verified="yes">
	<folder>screenshots</folder>
	<filename>_262.jpg</filename>
	<path>C:\Users\mrgam\Desktop\Ban\UCI\2019 Spring\CS 175\proj\TeamBEH\train\screenshots\_262.jpg</path>
	<source>
		<database>Unknown</database>
	</source>
	<size>
		<width>800</width>
		<height>500</height>
		<depth>3</depth>
	</size>
	<segmented>0</segmented>
	<object>
		<name>cow</name>
		<pose>Unspecified</pose>
		<truncated>0</truncated>
		<difficult>0</difficult>
		<bndbox>
			<xmin>63</xmin>
			<ymin>242</ymin>
			<xmax>160</xmax>
			<ymax>333</ymax>
		</bndbox>
	</object>
	<object>
		<name>sheep</name>
		<pose>Unspecified</pose>
		<truncated>0</truncated>
		<difficult>0</difficult>
		<bndbox>
			<xmin>171</xmin>
			<ymin>249</ymin>
			<xmax>222</xmax>
			<ymax>320</ymax>
		</bndbox>
	</object>
	<object>
		<name>sheep</name>
		<pose>Unspecified</pose>
		<truncated>0</truncated>
		<difficult>0</difficult>
		<bndbox>
			<xmin>243</xmin>
			<ymin>255</ymin>
			<xmax>324</xmax>
			<ymax>333</ymax>
		</bndbox>
	</object>
	<object>
		<name>cow</name>
		<pose>Unspecified</pose>
		<truncated>0</truncated>
		<difficult>0</difficult>
		<bndbox>
			<xmin>344</xmin>
			<ymin>250</ymin>
			<xmax>427</xmax>
			<ymax>353</ymax>
		</bndbox>
	</object>
	<object>
		<name>pig</name>
		<pose>Unspecified</pose>
		<truncated>0</truncated>
		<difficult>0</difficult>
		<bndbox>
			<xmin>637</xmin>
			<ymin>268</ymin>
			<xmax>704</xmax>
			<ymax>336</ymax>
		</bndbox>
	</object>
</annotation>
