<annotation>
	<folder>images</folder>
	<filename>_7.jpg</filename>
	<path>/Users/ed-1/Documents/cs175/training-set/images/_7.jpg</path>
	<source>
		<database>Unknown</database>
	</source>
	<size>
		<width>800</width>
		<height>500</height>
		<depth>3</depth>
	</size>
	<segmented>0</segmented>
	<object>
		<name>cow</name>
		<pose>Unspecified</pose>
		<truncated>0</truncated>
		<difficult>0</difficult>
		<bndbox>
			<xmin>370</xmin>
			<ymin>188</ymin>
			<xmax>438</xmax>
			<ymax>275</ymax>
		</bndbox>
	</object>
</annotation>
