<annotation>
	<folder>images</folder>
	<filename>_125.jpg</filename>
	<path>/Users/ed-1/Documents/cs175/training-set/images/_125.jpg</path>
	<source>
		<database>Unknown</database>
	</source>
	<size>
		<width>800</width>
		<height>500</height>
		<depth>3</depth>
	</size>
	<segmented>0</segmented>
	<object>
		<name>sheep</name>
		<pose>Unspecified</pose>
		<truncated>0</truncated>
		<difficult>0</difficult>
		<bndbox>
			<xmin>112</xmin>
			<ymin>197</ymin>
			<xmax>281</xmax>
			<ymax>305</ymax>
		</bndbox>
	</object>
	<object>
		<name>sheep</name>
		<pose>Unspecified</pose>
		<truncated>0</truncated>
		<difficult>0</difficult>
		<bndbox>
			<xmin>519</xmin>
			<ymin>192</ymin>
			<xmax>597</xmax>
			<ymax>258</ymax>
		</bndbox>
	</object>
	<object>
		<name>cow</name>
		<pose>Unspecified</pose>
		<truncated>0</truncated>
		<difficult>0</difficult>
		<bndbox>
			<xmin>619</xmin>
			<ymin>185</ymin>
			<xmax>706</xmax>
			<ymax>261</ymax>
		</bndbox>
	</object>
</annotation>
