<annotation>
	<folder>images</folder>
	<filename>_195.jpg</filename>
	<path>/Users/ed-1/Documents/cs175/training-set/images/_195.jpg</path>
	<source>
		<database>Unknown</database>
	</source>
	<size>
		<width>800</width>
		<height>500</height>
		<depth>3</depth>
	</size>
	<segmented>0</segmented>
	<object>
		<name>pig</name>
		<pose>Unspecified</pose>
		<truncated>1</truncated>
		<difficult>0</difficult>
		<bndbox>
			<xmin>1</xmin>
			<ymin>317</ymin>
			<xmax>213</xmax>
			<ymax>500</ymax>
		</bndbox>
	</object>
	<object>
		<name>cow</name>
		<pose>Unspecified</pose>
		<truncated>0</truncated>
		<difficult>0</difficult>
		<bndbox>
			<xmin>335</xmin>
			<ymin>200</ymin>
			<xmax>373</xmax>
			<ymax>235</ymax>
		</bndbox>
	</object>
	<object>
		<name>pig</name>
		<pose>Unspecified</pose>
		<truncated>0</truncated>
		<difficult>0</difficult>
		<bndbox>
			<xmin>269</xmin>
			<ymin>214</ymin>
			<xmax>313</xmax>
			<ymax>245</ymax>
		</bndbox>
	</object>
</annotation>
